[
  {
    "id": 1,
    "list": "추석세트",
    "item": [
      {
        "id": 1,
        "text": "홍삼,즙,건강세트"
      },
      {
        "id": 2,
        "text": "정육,가공육,건육"
      },
      {
        "id": 3,
        "text": "수산,건어물,젓갈"
      },
      {
        "id": 4,
        "text": "과일,견과,곡류"
      },
      {
        "id": 5,
        "text": "디저트,치즈,다과류"
      },
      {
        "id": 6,
        "text": "면,양념,오일"
      },
      {
        "id": 7,
        "text": "생활,뷰티"
      },
      {
        "id": 8,
        "text": "간편식,반찬"
      }
    ]
  },
  {
    "id": 2,
    "list": "채소",
    "item": [
      {
        "id": 1,
        "text": "친환경"
      },
      {
        "id": 2,
        "text": "제철과일"
      },
      {
        "id": 3,
        "text": "국산과일"
      },
      {
        "id": 4,
        "text": "수입과일"
      },
      {
        "id": 5,
        "text": "간편과일"
      },
      {
        "id": 6,
        "text": "냉동, 견과류"
      }
    ]
  },
  {
    "id": 3,
    "list": "수산,건어물",
    "item": [
      {
        "id": 1,
        "text": "제철수산"
      },
      {
        "id": 2,
        "text": "생선류"
      },
      {
        "id": 3,
        "text": "굴비,반건류"
      },
      {
        "id": 4,
        "text": "오징어,낙지,문어"
      },
      {
        "id": 5,
        "text": "새우,게,랍스터"
      },
      {
        "id": 6,
        "text": "해산물,조개류"
      },
      {
        "id": 7,
        "text": "수산가공품"
      },
      {
        "id": 8,
        "text": "김,미역,해조류"
      }
    ]
  },
  {
    "id": 4,
    "list": "정육,계란",
    "item": [
      {
        "id": 1,
        "text": "국내산 소고기"
      },
      {
        "id": 2,
        "text": "수입산 소고기"
      },
      {
        "id": 3,
        "text": "돼지고기"
      },
      {
        "id": 4,
        "text": "계란류"
      },
      {
        "id": 5,
        "text": "닭,오리고기"
      },
      {
        "id": 6,
        "text": "양념육,돈까스"
      }
    ]
  },
  {
    "id": 5,
    "list": "국,반찬,메인요리",
    "item": [
      {
        "id": 1,
        "text": "정육"
      },
      {
        "id": 2,
        "text": "국,탕,찌개"
      },
      {
        "id": 3,
        "text": "메인요리"
      },
      {
        "id": 4,
        "text": "일반반찬"
      },
      {
        "id": 5,
        "text": "김치,젓갈"
      },
      {
        "id": 6,
        "text": "두부,어묵"
      }
    ]
  },
  {
    "id": 6,
    "list": "샐러드,간편식",
    "item": [
      {
        "id": 1,
        "text": "샐러드"
      },
      {
        "id": 2,
        "text": "도시락,밥류"
      },
      {
        "id": 3,
        "text": "파스타,면류"
      },
      {
        "id": 4,
        "text": "떡볶이,튀김,순대"
      },
      {
        "id": 5,
        "text": "피자,핫도그"
      },
      {
        "id": 6,
        "text": "폭립,떡갈비"
      }
    ]
  },
  {
    "list": "면,양념,오일",
    "item": []
  },
  {
    "list": "생수,음료,우유",
    "item": []
  },
  {
    "list": "간식,과자,떡",
    "item": []
  },
  {
    "list": "베이커리,치즈,델리",
    "item": []
  },
  {
    "list": "건강식품",
    "item": []
  },
  {
    "list": "생활용품,리빙",
    "item": []
  },
  {
    "list": "스킨케어,메이크업",
    "item": []
  },
  {
    "list": "헤어바디,구강",
    "item": []
  },
  {
    "list": "주방용품",
    "item": []
  }
]
